{
    "ModCollectibleComponent": {
                                "DisplayNameLocalizationId" : "GAMEPLAY_COLLECTIBLE_TITL_RedA",
                                "DescriptionLocalizatonId" : "GAMEPLAY_COLLECTIBLE_DESC_RedA",
                                "InventoryActionLocalizationId" : "",
                                "WeightKG": 0,
                                "DaysToDecay" : 0,
                                "MaxHP" : 100,
                                "InitialCondition" : "Perfect",
                                "InventoryCategory" : "Tool",
                                "PickUpAudio" : "Play_SndInvGenericTiny",
                                "PutBackAudio" : "Play_SndInvGenericTiny",
                                "StowAudio" : "Play_InventoryStow",
                                "WornOutAudio" : "",
                                "InspectOnPickup" : true,
                                "InspectDistance" : 0.35,
                                "InspectAngles" : [-90, 0, 25],
                                "InspectOffset" : [0, -0.01, 0],
                                "InspectScale" :  [1, 1, 1],
                                "NormalModel" : "",
                                "InspectModel" : "",

                                "HudMessageLocalizationId" : "GAMEPLAY_COLLECTIBLE_TITL_RedA",
                                "NarrativeTextLocalizationId" : "GAMEPLAY_COLLECTIBLE_LORE_RedA",
                                "TextAlignment" : "Center"
                            }
}
